argshold/__init__.py
argshold/core/ArgsHolder.py
argshold/core/__init__.py
argshold/tests/__init__.py
argshold/tests/test_holder.py
argshold-2.0.0.dist-info/licenses/LICENSE.txt
argshold-2.0.0.dist-info/METADATA
argshold-2.0.0.dist-info/WHEEL
argshold-2.0.0.dist-info/top_level.txt
argshold-2.0.0.dist-info/RECORD
