Metadata-Version: 2.4
Name: argshold
Version: 2.0.0
Summary: This project provides holders for the arguments for callables.
Author-email: Johannes <johannes.programming@gmail.com>
License: The MIT License (MIT)
Project-URL: Download, https://pypi.org/project/argshold/#files
Project-URL: Index, https://pypi.org/project/argshold/
Project-URL: Source, https://github.com/johannes-programming/argshold/
Project-URL: Website, https://argshold.johannes-programming.online/
Classifier: Development Status :: 5 - Production/Stable
Classifier: License :: OSI Approved :: MIT License
Classifier: Natural Language :: English
Classifier: Operating System :: OS Independent
Classifier: Programming Language :: Python
Classifier: Programming Language :: Python :: 3
Classifier: Programming Language :: Python :: 3 :: Only
Classifier: Typing :: Typed
Requires-Python: >=3.11
License-File: LICENSE.txt
Requires-Dist: datarepr<2,>=1.0.1
Requires-Dist: frozendict<3,>=2.4.6
Requires-Dist: setdoc<2,>=1.2.6
Requires-Dist: unhash<2,>=1.0
Dynamic: license-file
